infi.sysv_service-0.1.18-py2.7-nspkg.pth
infi/sysv_service/__init__.py
infi/sysv_service/__version__.py
infi/sysv_service/tests.py
infi.sysv_service-0.1.18.dist-info/LICENSE
infi.sysv_service-0.1.18.dist-info/METADATA
infi.sysv_service-0.1.18.dist-info/WHEEL
infi.sysv_service-0.1.18.dist-info/entry_points.txt
infi.sysv_service-0.1.18.dist-info/namespace_packages.txt
infi.sysv_service-0.1.18.dist-info/top_level.txt
infi.sysv_service-0.1.18.dist-info/RECORD
