Metadata-Version: 2.1
Name: infi.sysv-service
Version: 0.1.18
Summary: cross-distribution module for managing Linux services
Home-page: https://github.com/Infinidat/infi.sysv_service
Author: Arnon Yaari
Author-email: arnony@infinidat.com
License: BSD
Platform: UNKNOWN
Classifier: Intended Audience :: Developers
Classifier: Intended Audience :: System Administrators
Classifier: License :: OSI Approved :: BSD License
Classifier: Operating System :: OS Independent
Classifier: Programming Language :: Python
Classifier: Programming Language :: Python :: 2
Classifier: Programming Language :: Python :: 3
Classifier: Topic :: Software Development :: Libraries :: Python Modules
Requires-Dist: psutil
Requires-Dist: setuptools
